globus_sdk_tokenstorage/__init__.py
globus_sdk_tokenstorage/abstract_base.py
globus_sdk_tokenstorage/base.py
globus_sdk_tokenstorage/file_adapters.py
globus_sdk_tokenstorage/sqlite_adapter.py
globus_sdk_tokenstorage/version.py
globus_sdk_tokenstorage-0.4.1.dist-info/COPYING
globus_sdk_tokenstorage-0.4.1.dist-info/LICENSE
globus_sdk_tokenstorage-0.4.1.dist-info/METADATA
globus_sdk_tokenstorage-0.4.1.dist-info/WHEEL
globus_sdk_tokenstorage-0.4.1.dist-info/top_level.txt
globus_sdk_tokenstorage-0.4.1.dist-info/RECORD
