Metadata-Version: 2.1
Name: globus-sdk-tokenstorage
Version: 0.4.1
Summary: Globus SDK TokenStorage Extension
Home-page: https://github.com/globus/globus-sdk-tokenstorage
Author: Stpehen Rosen
Author-email: sirosen@globus.org
License: UNKNOWN
Keywords: globus,sdk,contrib
Platform: UNKNOWN
Classifier: Development Status :: 3 - Alpha
Classifier: Intended Audience :: Developers
Classifier: License :: OSI Approved :: Apache Software License
Classifier: Operating System :: MacOS :: MacOS X
Classifier: Operating System :: Microsoft :: Windows
Classifier: Operating System :: POSIX
Classifier: Programming Language :: Python
Classifier: Programming Language :: Python :: 3.6
Classifier: Programming Language :: Python :: 3.7
Classifier: Programming Language :: Python :: 3.8
Classifier: Programming Language :: Python :: 3.9
Classifier: Topic :: Software Development :: Libraries :: Python Modules
Requires-Dist: globus-sdk (<4,>=1.6.1)
Provides-Extra: test
Requires-Dist: pytest (<4.0,>=3.7.4); extra == 'test'
Requires-Dist: pytest-cov (<3.0,>=2.5.1); extra == 'test'
Requires-Dist: pytest-xdist (<2.0,>=1.22.5); extra == 'test'
